treebeardhq/__init__.py
treebeardhq/batch.py
treebeardhq/constants.py
treebeardhq/context.py
treebeardhq/core.py
treebeardhq/log.py
treebeardhq-0.4.0.dist-info/METADATA
treebeardhq-0.4.0.dist-info/WHEEL
treebeardhq-0.4.0.dist-info/RECORD
