Metadata-Version: 2.4
Name: treebeardhq
Version: 0.4.0
Summary: The Treebeard Python SDK
Project-URL: Homepage, https://github.com/treebeardhq/sdk-python
Project-URL: Bug Tracker, https://github.com/treebeardhq/sdk-python/issues
Author-email: George Mayer <george@treebeardhq.com>
Classifier: License :: OSI Approved :: MIT License
Classifier: Operating System :: OS Independent
Classifier: Programming Language :: Python :: 3
Requires-Python: >=3.8
Requires-Dist: termcolor>=2.0.0
Provides-Extra: dev
Requires-Dist: black>=23.0.0; extra == 'dev'
Requires-Dist: build>=1.2.2; extra == 'dev'
Requires-Dist: mypy>=1.0.0; extra == 'dev'
Requires-Dist: pytest-cov>=4.0.0; extra == 'dev'
Requires-Dist: pytest>=7.0.0; extra == 'dev'
Requires-Dist: ruff>=0.0.290; extra == 'dev'
Provides-Extra: test
Requires-Dist: pytest-cov>=4.0.0; extra == 'test'
Requires-Dist: pytest-mock>=3.0.0; extra == 'test'
Requires-Dist: pytest>=7.0.0; extra == 'test'
